habushu_cucumber_formatter/__init__.py
habushu_cucumber_formatter/habushu_cucumber_formatter.py
habushu_cucumber_formatter-1.0.0.dist-info/LICENSE.txt
habushu_cucumber_formatter-1.0.0.dist-info/METADATA
habushu_cucumber_formatter-1.0.0.dist-info/WHEEL
habushu_cucumber_formatter-1.0.0.dist-info/RECORD
